LICENSE
README.md
pyproject.toml
setup.cfg
setup.py
src/spectroflat/__init__.py
src/spectroflat/analyzer.py
src/spectroflat.egg-info/PKG-INFO
src/spectroflat.egg-info/SOURCES.txt
src/spectroflat.egg-info/dependency_links.txt
src/spectroflat.egg-info/requires.txt
src/spectroflat.egg-info/top_level.txt
src/spectroflat/base/__init__.py
src/spectroflat/base/config.py
src/spectroflat/base/exceptions.py
src/spectroflat/base/logging.py
src/spectroflat/base/sensor_flat_config.py
src/spectroflat/base/smile_config.py
src/spectroflat/fitting/__init__.py
src/spectroflat/fitting/line.py
src/spectroflat/fitting/line_detector.py
src/spectroflat/fitting/line_fit.py
src/spectroflat/fitting/line_locator.py
src/spectroflat/inspection/__init__.py
src/spectroflat/inspection/flat_field_report.py
src/spectroflat/inspection/offset_map.py
src/spectroflat/inspection/pdf.py
src/spectroflat/sensor/__init__.py
src/spectroflat/sensor/artificial_flat.py
src/spectroflat/sensor/c2c_comp.py
src/spectroflat/sensor/flat.py
src/spectroflat/sensor/smooth_model.py
src/spectroflat/shift/__init__.py
src/spectroflat/shift/img_rotation.py
src/spectroflat/shift/sub_shift.py
src/spectroflat/smile/__init__.py
src/spectroflat/smile/alignment.py
src/spectroflat/smile/interpolated_correction.py
src/spectroflat/smile/offset_map.py
src/spectroflat/smile/smile_correction.py
src/spectroflat/smile/smile_detection.py
src/spectroflat/smile/smile_fit.py
src/spectroflat/smile/smoothing.py
src/spectroflat/utils/__init__.py
src/spectroflat/utils/collections.py
src/spectroflat/utils/ffing.py
src/spectroflat/utils/line_detection.py
src/spectroflat/utils/operations.py
src/spectroflat/utils/polynomial.py
src/spectroflat/utils/processing.py