Metadata-Version: 2.1
Name: spectroflat
Version: 2.0.0
Summary: Flat field and smile correction spectro-polarimetric solar images.
Home-page: https://gitlab.gwdg.de/hoelken/spectroflat
Author: Johannes Hölken
Author-email: hoelken@mps.mpg.de
Project-URL: Bug Tracker, https://gitlab.gwdg.de/hoelken/spectroflat/issues
Classifier: Programming Language :: Python :: 3
Classifier: License :: OSI Approved :: BSD License
Classifier: Operating System :: OS Independent
Requires-Python: >=3.8
License-File: LICENSE
Requires-Dist: scikit_image>=0.19
Requires-Dist: matplotlib>=3.5
Requires-Dist: numpy>=1.23
Requires-Dist: scipy>=1.9
Requires-Dist: qollib
